MANIFEST.in
README.rst
setup.py
maloja/__init__.py
maloja/broker.py
maloja/builder.py
maloja/cli.py
maloja/console.py
maloja/inspector.py
maloja/main.py
maloja/model.py
maloja/planner.py
maloja/surveyor.py
maloja/types.py
maloja.egg-info/PKG-INFO
maloja.egg-info/SOURCES.txt
maloja.egg-info/dependency_links.txt
maloja.egg-info/entry_points.txt
maloja.egg-info/not-zip-safe
maloja.egg-info/requires.txt
maloja.egg-info/top_level.txt
maloja/doc/api.rst
maloja/doc/cli.rst
maloja/doc/contribute.rst
maloja/doc/designfile.rst
maloja/doc/index.rst
maloja/doc/install.rst
maloja/doc/model.rst
maloja/doc/plugins.rst
maloja/doc/quickstart.rst
maloja/doc/_static/architecture.png
maloja/doc/html/api.html
maloja/doc/html/cli.html
maloja/doc/html/contribute.html
maloja/doc/html/designfile.html
maloja/doc/html/genindex.html
maloja/doc/html/index.html
maloja/doc/html/install.html
maloja/doc/html/model.html
maloja/doc/html/plugins.html
maloja/doc/html/py-modindex.html
maloja/doc/html/quickstart.html
maloja/doc/html/search.html
maloja/doc/html/searchindex.js
maloja/doc/html/_images/architecture.png
maloja/doc/html/_sources/api.txt
maloja/doc/html/_sources/cli.txt
maloja/doc/html/_sources/contribute.txt
maloja/doc/html/_sources/designfile.txt
maloja/doc/html/_sources/index.txt
maloja/doc/html/_sources/install.txt
maloja/doc/html/_sources/model.txt
maloja/doc/html/_sources/plugins.txt
maloja/doc/html/_sources/quickstart.txt
maloja/doc/html/_static/ajax-loader.gif
maloja/doc/html/_static/architecture.png
maloja/doc/html/_static/basic.css
maloja/doc/html/_static/comment-bright.png
maloja/doc/html/_static/comment-close.png
maloja/doc/html/_static/comment.png
maloja/doc/html/_static/doctools.js
maloja/doc/html/_static/down-pressed.png
maloja/doc/html/_static/down.png
maloja/doc/html/_static/file.png
maloja/doc/html/_static/jquery-1.11.1.js
maloja/doc/html/_static/jquery.js
maloja/doc/html/_static/minus.png
maloja/doc/html/_static/plus.png
maloja/doc/html/_static/pygments.css
maloja/doc/html/_static/searchtools.js
maloja/doc/html/_static/underscore-1.3.1.js
maloja/doc/html/_static/underscore.js
maloja/doc/html/_static/up-pressed.png
maloja/doc/html/_static/up.png
maloja/doc/html/_static/websupport.js
