Metadata-Version: 1.1
Name: maloja
Version: 0.7.0
Summary: Python toolkit for VMware operations.
Home-page: https://bitbucket.org/maloja/maloja
Author: D Haynes
Author-email: dave@thuswise.co.uk
License: UNKNOWN
Platform: UNKNOWN
Classifier: Operating System :: OS Independent
Classifier: Programming Language :: Python :: 3.4
Classifier: Programming Language :: Python :: 3.5
Classifier: License :: OSI Approved :: Apache Software License
